[
  {
    "id": "1897004569202450945",
    "created_at": "Tue Mar 04 19:21:48 +0000 2025",
    "full_text": "@RazorpayCare Request Team @Razorpay  To Acknowledge This Issue From Their End &amp; Provide Request No / Reference No Regarding The Same .To Provide Either Full Refund Or Delivery Of Good To Us And Also To Provide Expected Time Till When Our Issue Will Be Resolved. Shared Same Via DM Please Reply",
    "language": "en",
    "favorite_count": 0,
    "retweet_count": 0,
    "reply_count": 1,
    "quote_count": 0,
    "bookmark_count": 0,
    "view_count": 20,
    "user": {
      "id": "1377857102027268099",
      "name": "Mani Ratan Pratap Singh",
      "screen_name": "maniratanprata",
      "followers_count": 7,
      "following_count": 38,
      "is_verified": false,
      "profile_image_url": "https://pbs.twimg.com/profile_images/1657463956435509250/HT4F7oJQ_normal.jpg",
      "description": "A Simple Life Is The Best Version You Can Be."
    },
    "is_reply": true,
    "in_reply_to_tweet_id": "1896849457108697451",
    "in_reply_to_user": "RazorpayCare",
    "is_quote": false,
    "conversation_id": "1876048241030287757",
    "hashtags": [],
    "mentions": [
      {
        "screen_name": "RazorpayCare",
        "name": "Razorpay Care",
        "id": "807158172305625088"
      },
      {
        "screen_name": "Razorpay",
        "name": "Razorpay",
        "id": "2609379660"
      }
    ],
    "urls": [],
    "media": [],
    "tweet_url": "https://x.com/maniratanprata/status/1897004569202450945"
  },
  {
    "id": "1896999334190748042",
    "created_at": "Tue Mar 04 19:01:00 +0000 2025",
    "full_text": "No filters, no fluff!  \n\nAt TNM, we are committed to telling you the truth because you deserve news that is raw and reliable. \n\nScan the QR to support a newsroom that will always serve its audience and not those in power. https://t.co/6ZOluhmwvT https://t.co/bUqxKLdmCF",
    "language": "en",
    "favorite_count": 0,
    "retweet_count": 0,
    "reply_count": 0,
    "quote_count": 0,
    "bookmark_count": 0,
    "view_count": 570,
    "user": {
      "id": "2227695199",
      "name": "TheNewsMinute",
      "screen_name": "thenewsminute",
      "followers_count": 232831,
      "following_count": 1057,
      "is_verified": true,
      "profile_image_url": "https://pbs.twimg.com/profile_images/1408380639917711360/pl5Jepkq_normal.jpg",
      "description": "Look south, think TNM. News, ground reports and analysis from south India.\n\nFor subscription related queries: members@thenewsminute.com"
    },
    "is_reply": false,
    "in_reply_to_tweet_id": null,
    "in_reply_to_user": null,
    "is_quote": false,
    "conversation_id": "1896999334190748042",
    "hashtags": [],
    "mentions": [],
    "urls": [
      {
        "url": "https://t.co/6ZOluhmwvT",
        "expanded_url": "https://pages.razorpay.com/tnm-11th",
        "display_url": "pages.razorpay.com/tnm-11th"
      }
    ],
    "media": [
      {
        "type": "photo",
        "url": "https://pbs.twimg.com/media/GlJDCT4XMAAaInS.jpg",
        "expanded_url": "https://x.com/thenewsminute/status/1896999334190748042/photo/1"
      }
    ],
    "tweet_url": "https://x.com/thenewsminute/status/1896999334190748042"
  },
  {
    "id": "1896991377113981187",
    "created_at": "Tue Mar 04 18:29:23 +0000 2025",
    "full_text": "Day 7\nLooking for a data scientist role in India! Experienced in [your key skills, e.g., ML, NLP, Python, SQL. Open to opportunities in fintech, AI, and analytics.\n@TCS @Wipro @PayPal @Infosys @Razorpay @ZeptoNow @Flipkart @CRED_club  @SwiggyTech\n#DataScience #Hiring #jobsearch",
    "language": "en",
    "favorite_count": 1,
    "retweet_count": 0,
    "reply_count": 0,
    "quote_count": 0,
    "bookmark_count": 0,
    "view_count": 157,
    "user": {
      "id": "1021261453829931008",
      "name": "Ayan Talukdar",
      "screen_name": "ImAyanTalukdar",
      "followers_count": 137,
      "following_count": 249,
      "is_verified": false,
      "profile_image_url": "https://pbs.twimg.com/profile_images/1367942704210927616/K0w5WZNu_normal.jpg",
      "description": "Shatter the shackles through arts ||Data Scientist @Samsu g ||Intern @Samsung RnD Institute Noida ||Intern @FeynnLabs ||https://t.co/zdqSqUbYoX: NIT Sil"
    },
    "is_reply": false,
    "in_reply_to_tweet_id": null,
    "in_reply_to_user": null,
    "is_quote": false,
    "conversation_id": "1896991377113981187",
    "hashtags": [
      "DataScience",
      "Hiring",
      "jobsearch"
    ],
    "mentions": [
      {
        "screen_name": "TCS",
        "name": "Tata Consultancy Services",
        "id": "18929773"
      },
      {
        "screen_name": "Wipro",
        "name": "Wipro",
        "id": "14390109"
      },
      {
        "screen_name": "PayPal",
        "name": "PayPal",
        "id": "30018058"
      },
      {
        "screen_name": "Infosys",
        "name": "Infosys",
        "id": "14462907"
      },
      {
        "screen_name": "Razorpay",
        "name": "Razorpay",
        "id": "2609379660"
      },
      {
        "screen_name": "ZeptoNow",
        "name": "Zepto",
        "id": "1414590037123944456"
      },
      {
        "screen_name": "Flipkart",
        "name": "Flipkart",
        "id": "57947109"
      },
      {
        "screen_name": "CRED_club",
        "name": "CRED",
        "id": "1027264470370770945"
      },
      {
        "screen_name": "SwiggyTech",
        "name": "Swiggy Tech",
        "id": "1197020862420934657"
      }
    ],
    "urls": [],
    "media": [],
    "tweet_url": "https://x.com/ImAyanTalukdar/status/1896991377113981187"
  },
  {
    "id": "1896986500073709639",
    "created_at": "Tue Mar 04 18:10:00 +0000 2025",
    "full_text": "The future of millions of young Indians is at risk as India’s higher education system faces an unprecedented crisis.\n\nJohanna Deeksha is investigating irregularities in crucial exams held in the country.\n\nBut we need your support.\n\nPlease contribute: https://t.co/u8BRQVojCY https://t.co/pcouejPMMw",
    "language": "en",
    "favorite_count": 2,
    "retweet_count": 2,
    "reply_count": 0,
    "quote_count": 0,
    "bookmark_count": 1,
    "view_count": 1146,
    "user": {
      "id": "414946220",
      "name": "Scroll.in",
      "screen_name": "scroll_in",
      "followers_count": 470453,
      "following_count": 111,
      "is_verified": false,
      "profile_image_url": "https://pbs.twimg.com/profile_images/1605258806250070016/YGzA42cy_normal.jpg",
      "description": "The news that matters and the things that make life worth living. Become a Scroll Member today. https://t.co/nJZ81D6Etp"
    },
    "is_reply": false,
    "in_reply_to_tweet_id": null,
    "in_reply_to_user": null,
    "is_quote": false,
    "conversation_id": "1896986500073709639",
    "hashtags": [],
    "mentions": [],
    "urls": [
      {
        "url": "https://t.co/u8BRQVojCY",
        "expanded_url": "https://pages.razorpay.com/scrolleducationproject?utm_source=engagementblock",
        "display_url": "pages.razorpay.com/scrolleducatio…"
      }
    ],
    "media": [
      {
        "type": "photo",
        "url": "https://pbs.twimg.com/media/GlM71RvXYAALgh1.jpg",
        "expanded_url": "https://x.com/scroll_in/status/1896986500073709639/photo/1"
      }
    ],
    "tweet_url": "https://x.com/scroll_in/status/1896986500073709639"
  },
  {
    "id": "1896978565029355947",
    "created_at": "Tue Mar 04 17:38:28 +0000 2025",
    "full_text": "@adityakabra @ICICIBank @Razorpay It's true. In fact I didn't understand why there is a compulsion of the Current Account only. If there are one or two transactions monthly.",
    "language": "en",
    "favorite_count": 0,
    "retweet_count": 0,
    "reply_count": 0,
    "quote_count": 0,
    "bookmark_count": 0,
    "view_count": 83,
    "user": {
      "id": "1059792660",
      "name": "Prasad Pujari",
      "screen_name": "veeradutta_engg",
      "followers_count": 116,
      "following_count": 143,
      "is_verified": false,
      "profile_image_url": "https://pbs.twimg.com/profile_images/1772133295574409216/p_S4VA2x_normal.jpg",
      "description": "Brahman, Mechanical engineering, Co-founder Bharat CapiTAZ, Director Veeradutta Engg Pvt Ltd, Pune, stock market, Business Succession\nTweets are personal views."
    },
    "is_reply": true,
    "in_reply_to_tweet_id": "1896905260498903138",
    "in_reply_to_user": "adityakabra",
    "is_quote": false,
    "conversation_id": "1896904886245319085",
    "hashtags": [],
    "mentions": [
      {
        "screen_name": "adityakabra",
        "name": "ADITYA KABRA",
        "id": "126896627"
      },
      {
        "screen_name": "ICICIBank",
        "name": "ICICI Bank",
        "id": "419298953"
      },
      {
        "screen_name": "Razorpay",
        "name": "Razorpay",
        "id": "2609379660"
      }
    ],
    "urls": [],
    "media": [],
    "tweet_url": "https://x.com/veeradutta_engg/status/1896978565029355947"
  },
  {
    "id": "1896973641197477919",
    "created_at": "Tue Mar 04 17:18:54 +0000 2025",
    "full_text": "@AnanyaArya20 @Razorpay Same thing. Let's see...",
    "language": "en",
    "favorite_count": 0,
    "retweet_count": 0,
    "reply_count": 1,
    "quote_count": 0,
    "bookmark_count": 0,
    "view_count": 28,
    "user": {
      "id": "1612165063",
      "name": "தமீம் தமிழ்",
      "screen_name": "StaThameem",
      "followers_count": 3735,
      "following_count": 2790,
      "is_verified": false,
      "profile_image_url": "https://pbs.twimg.com/profile_images/1415548062462889987/vSttwt2a_normal.jpg",
      "description": "வாழ்க்கை யெனும் ஆற்றினிலே ஓர் கடற் சேராப் படகிவன்\nகடவுள் இருக்கான்னா கும்பிடு போட்டுட்டு\nபோயிட்டே இரு மத்தவன நோன்டாத!\nஇயற்கைத் தாயவள் பிள்ளை🍃🌬️\n❄தமீம்தமிழ்❄"
    },
    "is_reply": true,
    "in_reply_to_tweet_id": "1896973293951049950",
    "in_reply_to_user": "AnanyaArya20",
    "is_quote": false,
    "conversation_id": "1896776835062735105",
    "hashtags": [],
    "mentions": [
      {
        "screen_name": "AnanyaArya20",
        "name": "Ananya Arya",
        "id": "1225668926526214145"
      },
      {
        "screen_name": "Razorpay",
        "name": "Razorpay",
        "id": "2609379660"
      }
    ],
    "urls": [],
    "media": [],
    "tweet_url": "https://x.com/StaThameem/status/1896973641197477919"
  },
  {
    "id": "1896968033681465598",
    "created_at": "Tue Mar 04 16:56:37 +0000 2025",
    "full_text": "@Razorpay @AnmolJaggi This the proof BluSmart had sent for transfer of money to me. Why are you keeping it for 17 days. Contact me on surendra.m.arora@gmail.com https://t.co/8PrzxWqpbZ",
    "language": "en",
    "favorite_count": 0,
    "retweet_count": 0,
    "reply_count": 2,
    "quote_count": 0,
    "bookmark_count": 0,
    "view_count": 41,
    "user": {
      "id": "895667473650864129",
      "name": "Surendra Mohan Arora",
      "screen_name": "arorasmohan",
      "followers_count": 10,
      "following_count": 26,
      "is_verified": false,
      "profile_image_url": "https://abs.twimg.com/sticky/default_profile_images/default_profile_normal.png",
      "description": ""
    },
    "is_reply": false,
    "in_reply_to_tweet_id": null,
    "in_reply_to_user": "Razorpay",
    "is_quote": false,
    "conversation_id": "1896968033681465598",
    "hashtags": [],
    "mentions": [
      {
        "screen_name": "Razorpay",
        "name": "Razorpay",
        "id": "2609379660"
      },
      {
        "screen_name": "AnmolJaggi",
        "name": "Anmol Singh Jaggi",
        "id": "44919886"
      }
    ],
    "urls": [],
    "media": [
      {
        "type": "photo",
        "url": "https://pbs.twimg.com/media/GlNiX5eWsAA9g_S.jpg",
        "expanded_url": "https://x.com/arorasmohan/status/1896968033681465598/photo/1"
      }
    ],
    "tweet_url": "https://x.com/arorasmohan/status/1896968033681465598"
  },
  {
    "id": "1896967130501042356",
    "created_at": "Tue Mar 04 16:53:02 +0000 2025",
    "full_text": "@Razorpay @AnmolJaggi  pl see what BluSmart is saying. They say you are keeping my money https://t.co/Ida5uupOLa",
    "language": "en",
    "favorite_count": 0,
    "retweet_count": 0,
    "reply_count": 0,
    "quote_count": 0,
    "bookmark_count": 0,
    "view_count": 24,
    "user": {
      "id": "895667473650864129",
      "name": "Surendra Mohan Arora",
      "screen_name": "arorasmohan",
      "followers_count": 10,
      "following_count": 26,
      "is_verified": false,
      "profile_image_url": "https://abs.twimg.com/sticky/default_profile_images/default_profile_normal.png",
      "description": ""
    },
    "is_reply": false,
    "in_reply_to_tweet_id": null,
    "in_reply_to_user": "Razorpay",
    "is_quote": false,
    "conversation_id": "1896967130501042356",
    "hashtags": [],
    "mentions": [
      {
        "screen_name": "Razorpay",
        "name": "Razorpay",
        "id": "2609379660"
      },
      {
        "screen_name": "AnmolJaggi",
        "name": "Anmol Singh Jaggi",
        "id": "44919886"
      }
    ],
    "urls": [],
    "media": [
      {
        "type": "photo",
        "url": "https://pbs.twimg.com/media/GlNhjU_WYAAg7oH.jpg",
        "expanded_url": "https://x.com/arorasmohan/status/1896967130501042356/photo/1"
      }
    ],
    "tweet_url": "https://x.com/arorasmohan/status/1896967130501042356"
  },
  {
    "id": "1896965846758777060",
    "created_at": "Tue Mar 04 16:47:56 +0000 2025",
    "full_text": "@AnanyaArya20 @Razorpay Got the refund?\nAny updates?",
    "language": "en",
    "favorite_count": 0,
    "retweet_count": 0,
    "reply_count": 1,
    "quote_count": 0,
    "bookmark_count": 0,
    "view_count": 17,
    "user": {
      "id": "1612165063",
      "name": "தமீம் தமிழ்",
      "screen_name": "StaThameem",
      "followers_count": 3735,
      "following_count": 2790,
      "is_verified": false,
      "profile_image_url": "https://pbs.twimg.com/profile_images/1415548062462889987/vSttwt2a_normal.jpg",
      "description": "வாழ்க்கை யெனும் ஆற்றினிலே ஓர் கடற் சேராப் படகிவன்\nகடவுள் இருக்கான்னா கும்பிடு போட்டுட்டு\nபோயிட்டே இரு மத்தவன நோன்டாத!\nஇயற்கைத் தாயவள் பிள்ளை🍃🌬️\n❄தமீம்தமிழ்❄"
    },
    "is_reply": true,
    "in_reply_to_tweet_id": "1896776835062735105",
    "in_reply_to_user": "AnanyaArya20",
    "is_quote": false,
    "conversation_id": "1896776835062735105",
    "hashtags": [],
    "mentions": [
      {
        "screen_name": "AnanyaArya20",
        "name": "Ananya Arya",
        "id": "1225668926526214145"
      },
      {
        "screen_name": "Razorpay",
        "name": "Razorpay",
        "id": "2609379660"
      }
    ],
    "urls": [],
    "media": [],
    "tweet_url": "https://x.com/StaThameem/status/1896965846758777060"
  },
  {
    "id": "1896964835075903760",
    "created_at": "Tue Mar 04 16:43:55 +0000 2025",
    "full_text": "Hi @IRCTCofficial and @IDFCFIRSTBank \n\nI received these mail and sms today mentioning that the refund has been processed by yesterday night itself. \nBut still I haven't received the refund yet.\n\n#IDFC #IRCTC #IndianRailways #railmadad #razorpay #eticket #Refund https://t.co/YUlgoQu8xS",
    "language": "en",
    "favorite_count": 0,
    "retweet_count": 0,
    "reply_count": 1,
    "quote_count": 0,
    "bookmark_count": 0,
    "view_count": 232,
    "user": {
      "id": "1612165063",
      "name": "தமீம் தமிழ்",
      "screen_name": "StaThameem",
      "followers_count": 3735,
      "following_count": 2790,
      "is_verified": false,
      "profile_image_url": "https://pbs.twimg.com/profile_images/1415548062462889987/vSttwt2a_normal.jpg",
      "description": "வாழ்க்கை யெனும் ஆற்றினிலே ஓர் கடற் சேராப் படகிவன்\nகடவுள் இருக்கான்னா கும்பிடு போட்டுட்டு\nபோயிட்டே இரு மத்தவன நோன்டாத!\nஇயற்கைத் தாயவள் பிள்ளை🍃🌬️\n❄தமீம்தமிழ்❄"
    },
    "is_reply": false,
    "in_reply_to_tweet_id": null,
    "in_reply_to_user": null,
    "is_quote": false,
    "conversation_id": "1896964835075903760",
    "hashtags": [
      "IDFC",
      "IRCTC",
      "IndianRailways",
      "railmadad",
      "razorpay",
      "eticket",
      "Refund"
    ],
    "mentions": [
      {
        "screen_name": "IRCTCofficial",
        "name": "IRCTC",
        "id": "141176075"
      },
      {
        "screen_name": "IDFCFIRSTBank",
        "name": "IDFC FIRST Bank",
        "id": "3305197135"
      }
    ],
    "urls": [],
    "media": [
      {
        "type": "photo",
        "url": "https://pbs.twimg.com/media/GlNfJx4WAAAO63n.jpg",
        "expanded_url": "https://x.com/StaThameem/status/1896964835075903760/photo/1"
      },
      {
        "type": "photo",
        "url": "https://pbs.twimg.com/media/GlNfJx5WkAAimGw.jpg",
        "expanded_url": "https://x.com/StaThameem/status/1896964835075903760/photo/1"
      }
    ],
    "tweet_url": "https://x.com/StaThameem/status/1896964835075903760"
  },
  {
    "id": "1896964477360480625",
    "created_at": "Tue Mar 04 16:42:29 +0000 2025",
    "full_text": "@AnmolJaggi No progress in my refund case despite repeated assurances from Shariat and Rahul. The blame is being put on payment gateway @Razorpay but I am surprised you can't handle them despite giving them massive business. How long can you grow if can't resolve a tiny issue. Very sad.",
    "language": "en",
    "favorite_count": 0,
    "retweet_count": 0,
    "reply_count": 1,
    "quote_count": 0,
    "bookmark_count": 0,
    "view_count": 26,
    "user": {
      "id": "895667473650864129",
      "name": "Surendra Mohan Arora",
      "screen_name": "arorasmohan",
      "followers_count": 10,
      "following_count": 26,
      "is_verified": false,
      "profile_image_url": "https://abs.twimg.com/sticky/default_profile_images/default_profile_normal.png",
      "description": ""
    },
    "is_reply": true,
    "in_reply_to_tweet_id": "1892501998315933994",
    "in_reply_to_user": "arorasmohan",
    "is_quote": false,
    "conversation_id": "1891868000883556407",
    "hashtags": [],
    "mentions": [
      {
        "screen_name": "AnmolJaggi",
        "name": "Anmol Singh Jaggi",
        "id": "44919886"
      },
      {
        "screen_name": "Razorpay",
        "name": "Razorpay",
        "id": "2609379660"
      }
    ],
    "urls": [],
    "media": [],
    "tweet_url": "https://x.com/arorasmohan/status/1896964477360480625"
  },
  {
    "id": "1896954497278394572",
    "created_at": "Tue Mar 04 16:02:50 +0000 2025",
    "full_text": "🚀 Top 10 Global Fintech Cities in 2024!\n\n1️⃣ San Francisco (Stripe, Robinhood)\n2️⃣ New York (Plaid, Betterment)\n3️⃣ London (Revolut, Wise)\n4️⃣ São Paulo (Nubank, open banking leader)\n5️⃣ Bangalore (Razorpay, digital payments hub)\n\nRead more: https://t.co/cjNWnaCc4w https://t.co/MuIbpHRzaj",
    "language": "en",
    "favorite_count": 0,
    "retweet_count": 0,
    "reply_count": 0,
    "quote_count": 0,
    "bookmark_count": 0,
    "view_count": 101,
    "user": {
      "id": "1707104129976283136",
      "name": "Forbes Cyprus The Future of Fintech Summit",
      "screen_name": "ForbesCY_FOFS",
      "followers_count": 57,
      "following_count": 60,
      "is_verified": false,
      "profile_image_url": "https://pbs.twimg.com/profile_images/1780506159658487808/r72xK4LA_normal.jpg",
      "description": "Join Forbes The Future of Fintech Summit. \nWe’ve been bringing fintech executives, investors, policymakers, and fintech experts together."
    },
    "is_reply": false,
    "in_reply_to_tweet_id": null,
    "in_reply_to_user": null,
    "is_quote": false,
    "conversation_id": "1896954497278394572",
    "hashtags": [],
    "mentions": [],
    "urls": [
      {
        "url": "https://t.co/cjNWnaCc4w",
        "expanded_url": "https://thefuturemedia.eu/top-10-global-cities-driving-fintech-innovation-in-2024/",
        "display_url": "thefuturemedia.eu/top-10-global-…"
      }
    ],
    "media": [
      {
        "type": "photo",
        "url": "https://pbs.twimg.com/media/GlNWDZFW8AAf97F.png",
        "expanded_url": "https://x.com/ForbesCY_FOFS/status/1896954497278394572/photo/1"
      }
    ],
    "tweet_url": "https://x.com/ForbesCY_FOFS/status/1896954497278394572"
  },
  {
    "id": "1896950009850900520",
    "created_at": "Tue Mar 04 15:45:00 +0000 2025",
    "full_text": "The future of millions of young Indians is at risk as India’s higher education system faces an unprecedented crisis.\n\nJohanna Deeksha is investigating irregularities in crucial exams held in the country.\n\nBut we need your support.\n\nConsider contributing: https://t.co/u8BRQVnLNq https://t.co/nQfQDTHck9",
    "language": "en",
    "favorite_count": 2,
    "retweet_count": 2,
    "reply_count": 0,
    "quote_count": 0,
    "bookmark_count": 1,
    "view_count": 732,
    "user": {
      "id": "414946220",
      "name": "Scroll.in",
      "screen_name": "scroll_in",
      "followers_count": 470453,
      "following_count": 111,
      "is_verified": false,
      "profile_image_url": "https://pbs.twimg.com/profile_images/1605258806250070016/YGzA42cy_normal.jpg",
      "description": "The news that matters and the things that make life worth living. Become a Scroll Member today. https://t.co/nJZ81D6Etp"
    },
    "is_reply": false,
    "in_reply_to_tweet_id": null,
    "in_reply_to_user": null,
    "is_quote": false,
    "conversation_id": "1896950009850900520",
    "hashtags": [],
    "mentions": [],
    "urls": [
      {
        "url": "https://t.co/u8BRQVnLNq",
        "expanded_url": "https://pages.razorpay.com/scrolleducationproject?utm_source=engagementblock",
        "display_url": "pages.razorpay.com/scrolleducatio…"
      }
    ],
    "media": [
      {
        "type": "photo",
        "url": "https://pbs.twimg.com/media/GlM6Ls7WAAA380S.jpg",
        "expanded_url": "https://x.com/scroll_in/status/1896950009850900520/photo/1"
      }
    ],
    "tweet_url": "https://x.com/scroll_in/status/1896950009850900520"
  },
  {
    "id": "1896947210899825005",
    "created_at": "Tue Mar 04 15:33:53 +0000 2025",
    "full_text": "🎉 TNM turns 11, and we’re celebrating with a Buy 1, Gift 1 Subscription!\n\nSubscribe to TNM-NL and gift a friend or family member a year of independent journalism—because good news deserves to be shared.\n\nJoin the movement:https://t.co/6ZOluhn4lr",
    "language": "en",
    "favorite_count": 1,
    "retweet_count": 0,
    "reply_count": 0,
    "quote_count": 0,
    "bookmark_count": 0,
    "view_count": 501,
    "user": {
      "id": "2227695199",
      "name": "TheNewsMinute",
      "screen_name": "thenewsminute",
      "followers_count": 232831,
      "following_count": 1057,
      "is_verified": true,
      "profile_image_url": "https://pbs.twimg.com/profile_images/1408380639917711360/pl5Jepkq_normal.jpg",
      "description": "Look south, think TNM. News, ground reports and analysis from south India.\n\nFor subscription related queries: members@thenewsminute.com"
    },
    "is_reply": true,
    "in_reply_to_tweet_id": "1896947208244895930",
    "in_reply_to_user": "thenewsminute",
    "is_quote": false,
    "conversation_id": "1896947205925486770",
    "hashtags": [],
    "mentions": [],
    "urls": [
      {
        "url": "https://t.co/6ZOluhn4lr",
        "expanded_url": "https://pages.razorpay.com/tnm-11th",
        "display_url": "pages.razorpay.com/tnm-11th"
      }
    ],
    "media": [],
    "tweet_url": "https://x.com/thenewsminute/status/1896947210899825005"
  },
  {
    "id": "1896928128221794365",
    "created_at": "Tue Mar 04 14:18:03 +0000 2025",
    "full_text": "@gupta_shubham0 Hi Shubham, we are here with you over a DM. Regards, Team Razorpay",
    "language": "en",
    "favorite_count": 0,
    "retweet_count": 0,
    "reply_count": 1,
    "quote_count": 0,
    "bookmark_count": 0,
    "view_count": 16,
    "user": {
      "id": "807158172305625088",
      "name": "Razorpay Care",
      "screen_name": "RazorpayCare",
      "followers_count": 4586,
      "following_count": 2,
      "is_verified": true,
      "profile_image_url": "https://pbs.twimg.com/profile_images/911111218940616705/8A3c7lFO_normal.jpg",
      "description": "This is the Twitter handle for @Razorpay Support. For a quick resolution please raise a request here: https://t.co/kNmRzkT3xk"
    },
    "is_reply": true,
    "in_reply_to_tweet_id": "1896867437804662842",
    "in_reply_to_user": "gupta_shubham0",
    "is_quote": false,
    "conversation_id": "1896867437804662842",
    "hashtags": [],
    "mentions": [
      {
        "screen_name": "gupta_shubham0",
        "name": "Shubham kumar Gupta",
        "id": "1401960303626100758"
      }
    ],
    "urls": [],
    "media": [],
    "tweet_url": "https://x.com/RazorpayCare/status/1896928128221794365"
  },
  {
    "id": "1896922814114041934",
    "created_at": "Tue Mar 04 13:56:56 +0000 2025",
    "full_text": "The future of millions of young Indians is at risk as India’s higher education system faces an unprecedented crisis.\n\nJohanna Deeksha is investigating irregularities in crucial exams held in the country.\n\nBut we need your support.\n\nConsider contributing: https://t.co/u8BRQVojCY https://t.co/kCCZY1nx6e",
    "language": "en",
    "favorite_count": 1,
    "retweet_count": 0,
    "reply_count": 0,
    "quote_count": 0,
    "bookmark_count": 0,
    "view_count": 603,
    "user": {
      "id": "414946220",
      "name": "Scroll.in",
      "screen_name": "scroll_in",
      "followers_count": 470453,
      "following_count": 111,
      "is_verified": false,
      "profile_image_url": "https://pbs.twimg.com/profile_images/1605258806250070016/YGzA42cy_normal.jpg",
      "description": "The news that matters and the things that make life worth living. Become a Scroll Member today. https://t.co/nJZ81D6Etp"
    },
    "is_reply": false,
    "in_reply_to_tweet_id": null,
    "in_reply_to_user": null,
    "is_quote": false,
    "conversation_id": "1896922814114041934",
    "hashtags": [],
    "mentions": [],
    "urls": [
      {
        "url": "https://t.co/u8BRQVojCY",
        "expanded_url": "https://pages.razorpay.com/scrolleducationproject?utm_source=engagementblock",
        "display_url": "pages.razorpay.com/scrolleducatio…"
      }
    ],
    "media": [
      {
        "type": "photo",
        "url": "https://pbs.twimg.com/media/GlM5OoMWwAALhRP.jpg",
        "expanded_url": "https://x.com/scroll_in/status/1896922814114041934/photo/1"
      }
    ],
    "tweet_url": "https://x.com/scroll_in/status/1896922814114041934"
  },
  {
    "id": "1896920855680360521",
    "created_at": "Tue Mar 04 13:49:09 +0000 2025",
    "full_text": "Razorpay is genuinely the Stripe of India. But that does not giving them enough credit.\n\nEven if their dashboard is slow, the tiny features in their products are so well thought out (e.g., autofill links for payment pages). \n\nOthers aren't even playing catch-up at this point.",
    "language": "en",
    "favorite_count": 4,
    "retweet_count": 1,
    "reply_count": 1,
    "quote_count": 0,
    "bookmark_count": 0,
    "view_count": 289,
    "user": {
      "id": "119755826",
      "name": "Mani",
      "screen_name": "megabored",
      "followers_count": 881,
      "following_count": 546,
      "is_verified": true,
      "profile_image_url": "https://pbs.twimg.com/profile_images/1764004424102686720/k1eVsx4b_normal.jpg",
      "description": "Product manager who codes. \n\nBuilding https://t.co/3OtfJ2LxaR with @fiendingforcake . \n\nAlso Building https://t.co/TKaPHm1Ndl over free time 👀"
    },
    "is_reply": false,
    "in_reply_to_tweet_id": null,
    "in_reply_to_user": null,
    "is_quote": false,
    "conversation_id": "1896920855680360521",
    "hashtags": [],
    "mentions": [],
    "urls": [],
    "media": [],
    "tweet_url": "https://x.com/megabored/status/1896920855680360521"
  },
  {
    "id": "1896919085767938197",
    "created_at": "Tue Mar 04 13:42:07 +0000 2025",
    "full_text": "@Advsaifalam Hi Saif, we sincerely apologize for the issues you’ve encountered. Please send us a DM with your Merchant ID or contact number and brief of your concern, and we’ll get to the bottom of this as quickly as possible! Regard, Team Razorpay https://t.co/K5EfXqMykd",
    "language": "en",
    "favorite_count": 1,
    "retweet_count": 0,
    "reply_count": 0,
    "quote_count": 0,
    "bookmark_count": 0,
    "view_count": 17,
    "user": {
      "id": "807158172305625088",
      "name": "Razorpay Care",
      "screen_name": "RazorpayCare",
      "followers_count": 4586,
      "following_count": 2,
      "is_verified": true,
      "profile_image_url": "https://pbs.twimg.com/profile_images/911111218940616705/8A3c7lFO_normal.jpg",
      "description": "This is the Twitter handle for @Razorpay Support. For a quick resolution please raise a request here: https://t.co/kNmRzkT3xk"
    },
    "is_reply": true,
    "in_reply_to_tweet_id": "1896859569391084031",
    "in_reply_to_user": "Advsaifalam",
    "is_quote": false,
    "conversation_id": "1896859569391084031",
    "hashtags": [],
    "mentions": [
      {
        "screen_name": "Advsaifalam",
        "name": "Advocate Saif Alam",
        "id": "1668072205"
      }
    ],
    "urls": [
      {
        "url": "https://t.co/K5EfXqMykd",
        "expanded_url": "https://x.com/messages/compose?recipient_id=807158172305625088",
        "display_url": "x.com/messages/compo…"
      }
    ],
    "media": [],
    "tweet_url": "https://x.com/RazorpayCare/status/1896919085767938197"
  },
  {
    "id": "1896910513252323822",
    "created_at": "Tue Mar 04 13:08:03 +0000 2025",
    "full_text": "@AshTheBuilderr if you're in india, maybe razorpay. otherwise, checkout lemonsqueezy",
    "language": "en",
    "favorite_count": 0,
    "retweet_count": 0,
    "reply_count": 0,
    "quote_count": 0,
    "bookmark_count": 0,
    "view_count": 51,
    "user": {
      "id": "1308308307417890816",
      "name": "shobhit",
      "screen_name": "shbhtngpl",
      "followers_count": 832,
      "following_count": 216,
      "is_verified": true,
      "profile_image_url": "https://pbs.twimg.com/profile_images/1595381969990217728/WLhyEQ6C_normal.jpg",
      "description": "building tools to get answers. i stream code and chess on weekends https://t.co/V0JxRwEeIX"
    },
    "is_reply": false,
    "in_reply_to_tweet_id": null,
    "in_reply_to_user": null,
    "is_quote": false,
    "conversation_id": "1896909358623293942",
    "hashtags": [],
    "mentions": [],
    "urls": [],
    "media": [],
    "tweet_url": "https://x.com/shbhtngpl/status/1896910513252323822"
  }
]